{"metadata":{"version":4,"city":"Goiânia","source":"goiania_local_first_index_v3","generatedAt":"2026-06-06T02:57:15.084Z","bairroKey":"ACALANTO","bairroLabel":"Acalanto","totalKeys":129,"totalCandidates":135},"index":{"ACALANTO|8|APM":[{"b":"Acalanto","q":"8","l":"APM","r":"R Naoqui","d":11.86,"c":"HIGH","lat":-16.7347175,"lng":-49.2275099,"si":118673},{"b":"Acalanto","q":"8","l":"APM","r":"AL Inan","d":16.33,"c":"HIGH","lat":-16.7352329,"lng":-49.2267567,"si":116467},{"b":"Acalanto","q":"8","l":"APM","r":"R Ueriri","d":19.01,"c":"HIGH","lat":-16.7353646,"lng":-49.2273854,"si":116466},{"b":"Acalanto","q":"8","l":"APM","r":"AV Bela Vista","d":27.23,"c":"HIGH","lat":-16.7362025,"lng":-49.2265082,"si":106815}],"ACALANTO|4|1 2":[{"b":"Acalanto","q":"4","l":"1/2","r":"R Ocanan","d":35.86,"c":"HIGH","lat":-16.7320696,"lng":-49.2278294,"si":106816}],"ACALANTO|7|APM":[{"b":"Acalanto","q":"7","l":"APM","r":"AL Inan","d":11.11,"c":"HIGH","lat":-16.7355571,"lng":-49.2264219,"si":107109}],"ACALANTO|7|2":[{"b":"Acalanto","q":"7","l":"2","r":"R Irariê","d":27.05,"c":"HIGH","lat":-16.7348938,"lng":-49.2262432,"si":110536}],"ACALANTO|7|9":[{"b":"Acalanto","q":"7","l":"9","r":"R Canambé","d":20.1,"c":"HIGH","lat":-16.7356875,"lng":-49.2262699,"si":110559}],"ACALANTO|7|5":[{"b":"Acalanto","q":"7","l":"5","r":"R Irariê","d":21.42,"c":"HIGH","lat":-16.7351634,"lng":-49.2258472,"si":110596}],"ACALANTO|7|15":[{"b":"Acalanto","q":"7","l":"15","r":"R Canambé","d":28.06,"c":"HIGH","lat":-16.7360617,"lng":-49.2259686,"si":110624}],"ACALANTO|7|3":[{"b":"Acalanto","q":"7","l":"3","r":"R Irariê","d":28.27,"c":"HIGH","lat":-16.7348427,"lng":-49.2260793,"si":110640}],"ACALANTO|7|6":[{"b":"Acalanto","q":"7","l":"6","r":"R Irariê","d":29.6,"c":"HIGH","lat":-16.7353488,"lng":-49.2259487,"si":110644}],"ACALANTO|7|1":[{"b":"Acalanto","q":"7","l":"1","r":"R Irariê","d":19.43,"c":"HIGH","lat":-16.7350151,"lng":-49.2264454,"si":110649}],"ACALANTO|7|16":[{"b":"Acalanto","q":"7","l":"16","r":"R Canambé","d":20.8,"c":"HIGH","lat":-16.7360448,"lng":-49.2261715,"si":110668}],"ACALANTO|7|4":[{"b":"Acalanto","q":"7","l":"4","r":"R Irariê","d":19.74,"c":"HIGH","lat":-16.7349415,"lng":-49.2259398,"si":110748}],"ACALANTO|7|12":[{"b":"Acalanto","q":"7","l":"12","r":"R Canambé","d":18.58,"c":"HIGH","lat":-16.7356552,"lng":-49.2257819,"si":110806}],"ACALANTO|7|13":[{"b":"Acalanto","q":"7","l":"13","r":"R Canambé","d":18.01,"c":"HIGH","lat":-16.7358534,"lng":-49.2257447,"si":110810}],"ACALANTO|7|7":[{"b":"Acalanto","q":"7","l":"7","r":"R Irariê","d":27.77,"c":"HIGH","lat":-16.7353895,"lng":-49.2261791,"si":110831}],"ACALANTO|7|10":[{"b":"Acalanto","q":"7","l":"10","r":"R Canambé","d":26.47,"c":"HIGH","lat":-16.7355934,"lng":-49.2261311,"si":110857}],"ACALANTO|7|14":[{"b":"Acalanto","q":"7","l":"14","r":"R Canambé","d":29.37,"c":"HIGH","lat":-16.7360182,"lng":-49.2257716,"si":110887}],"ACALANTO|7|11":[{"b":"Acalanto","q":"7","l":"11","r":"R Canambé","d":28.79,"c":"HIGH","lat":-16.7355234,"lng":-49.225865,"si":110900}],"ACALANTO|7|8":[{"b":"Acalanto","q":"7","l":"8","r":"R Irariê","d":20.07,"c":"HIGH","lat":-16.7353537,"lng":-49.2263248,"si":110914}],"ACALANTO|6|APM":[{"b":"Acalanto","q":"6","l":"APM","r":"R Naoqui","d":12.56,"c":"HIGH","lat":-16.7345229,"lng":-49.2276506,"si":116468},{"b":"Acalanto","q":"6","l":"APM","r":"R Diaran","d":17.95,"c":"HIGH","lat":-16.733903,"lng":-49.2278429,"si":116472},{"b":"Acalanto","q":"6","l":"APM","r":"AL Inan","d":23.8,"c":"HIGH","lat":-16.7337495,"lng":-49.2272103,"si":116471}],"ACALANTO|5|APM":[{"b":"Acalanto","q":"5","l":"APM","r":"AL Inan","d":14.14,"c":"HIGH","lat":-16.7329816,"lng":-49.2270397,"si":116469},{"b":"Acalanto","q":"5","l":"APM","r":"AL Inan","d":14.59,"c":"HIGH","lat":-16.7336682,"lng":-49.2268602,"si":116470}],"ACALANTO|8|32":[{"b":"Acalanto","q":"8","l":"32","r":"AV Angélica","d":16.72,"c":"HIGH","lat":-16.7360324,"lng":-49.2278148,"si":117657}],"ACALANTO|8|16":[{"b":"Acalanto","q":"8","l":"16","r":"R Deacon","d":17.03,"c":"HIGH","lat":-16.7347554,"lng":-49.2269007,"si":118652}],"ACALANTO|8|15":[{"b":"Acalanto","q":"8","l":"15","r":"R Naoqui","d":19.42,"c":"HIGH","lat":-16.7346841,"lng":-49.227056,"si":118653}],"ACALANTO|8|21":[{"b":"Acalanto","q":"8","l":"21","r":"R Ueriri","d":10.44,"c":"HIGH","lat":-16.735146,"lng":-49.2275623,"si":118654}],"ACALANTO|8|12":[{"b":"Acalanto","q":"8","l":"12","r":"R Deacon","d":12.15,"c":"HIGH","lat":-16.7350849,"lng":-49.2273363,"si":118655}],"ACALANTO|8|13":[{"b":"Acalanto","q":"8","l":"13","r":"R Deacon","d":28.17,"c":"HIGH","lat":-16.734869,"lng":-49.2273707,"si":118656}],"ACALANTO|8|20":[{"b":"Acalanto","q":"8","l":"20","r":"R Ueriri","d":28.03,"c":"HIGH","lat":-16.7349231,"lng":-49.2276038,"si":118657}],"ACALANTO|8|19":[{"b":"Acalanto","q":"8","l":"19","r":"R Naoqui","d":19.75,"c":"HIGH","lat":-16.7348485,"lng":-49.2277625,"si":118658}],"ACALANTO|8|17":[{"b":"Acalanto","q":"8","l":"17","r":"R Ueriri","d":19.61,"c":"HIGH","lat":-16.7350028,"lng":-49.2281067,"si":118659}],"ACALANTO|5|APM C31":[{"b":"Acalanto","q":"5","l":"APM-C31","r":"R Ocanan","d":12.07,"c":"HIGH","lat":-16.7321934,"lng":-49.2264792,"si":119128}],"ACALANTO|5|APM C25":[{"b":"Acalanto","q":"5","l":"APM-C25","r":"R Naoqui","d":12.16,"c":"HIGH","lat":-16.734169,"lng":-49.2260727,"si":119174}],"ACALANTO|5|APM C30":[{"b":"Acalanto","q":"5","l":"APM-C30","r":"AL Inan","d":6.32,"c":"HIGH","lat":-16.7323841,"lng":-49.2272709,"si":120153}],"ACALANTO|7|APM C26":[{"b":"Acalanto","q":"7","l":"APM-C26","r":"AL Inan","d":12.69,"c":"HIGH","lat":-16.734613,"lng":-49.2268833,"si":120154}],"ACALANTO|5|APM C27":[{"b":"Acalanto","q":"5","l":"APM-C27","r":"AL Inan","d":2.53,"c":"HIGH","lat":-16.7343448,"lng":-49.2268092,"si":120155}],"ACALANTO|8|APM C21":[{"b":"Acalanto","q":"8","l":"APM-C21","r":"AL Inan","d":7.49,"c":"HIGH","lat":-16.7345294,"lng":-49.2267112,"si":120156}],"ACALANTO|8|APM C18":[{"b":"Acalanto","q":"8","l":"APM-C18","r":"AV Angélica","d":10.59,"c":"HIGH","lat":-16.7348887,"lng":-49.228236,"si":120159}],"ACALANTO|6|APM C15":[{"b":"Acalanto","q":"6","l":"APM C15","r":"AL Inan","d":7.3,"c":"HIGH","lat":-16.7343036,"lng":-49.2267734,"si":120160}],"ACALANTO|4|3 4":[{"b":"Acalanto","q":"4","l":"3/4","r":"R Ocanan","d":36.26,"c":"HIGH","lat":-16.7322662,"lng":-49.2286868,"si":132462}],"ACALANTO|4|7 8":[{"b":"Acalanto","q":"4","l":"7/8","r":"R Leran","d":42.53,"c":"HIGH","lat":-16.7313618,"lng":-49.2279851,"si":132463}],"ACALANTO|4|5 6":[{"b":"Acalanto","q":"4","l":"5/6","r":"AV Angélica","d":52.57,"c":"MEDIUM","lat":-16.7315918,"lng":-49.2288664,"si":132466}],"ACALANTO|8|23":[{"b":"Acalanto","q":"8","l":"23","r":"R Ueriri","d":26.82,"c":"HIGH","lat":-16.7353795,"lng":-49.2278312,"si":135295}],"ACALANTO|6|21":[{"b":"Acalanto","q":"6","l":"21","r":"R Diaran","d":11.16,"c":"HIGH","lat":-16.7336742,"lng":-49.2279902,"si":140415}],"ACALANTO|6|13":[{"b":"Acalanto","q":"6","l":"13","r":"R Maiti","d":30.8,"c":"HIGH","lat":-16.733415,"lng":-49.2278651,"si":140416}],"ACALANTO|6|15":[{"b":"Acalanto","q":"6","l":"15","r":"R Maiti","d":29.52,"c":"HIGH","lat":-16.7331853,"lng":-49.2274969,"si":140417}],"ACALANTO|6|APM C12":[{"b":"Acalanto","q":"6","l":"APM-C12","r":"R Diaran","d":50.93,"c":"MEDIUM","lat":-16.733241,"lng":-49.2280051,"si":140418}],"ACALANTO|6|23":[{"b":"Acalanto","q":"6","l":"23","r":"R Diaran","d":28.33,"c":"HIGH","lat":-16.7339121,"lng":-49.2283166,"si":254017}],"ACALANTO|6|30":[{"b":"Acalanto","q":"6","l":"30","r":"R Naoqui","d":18.91,"c":"HIGH","lat":-16.7345262,"lng":-49.2279226,"si":254018}],"ACALANTO|8|28":[{"b":"Acalanto","q":"8","l":"28","r":"R Anarcan","d":12.89,"c":"HIGH","lat":-16.7356415,"lng":-49.2274173,"si":262538}],"ACALANTO|5|11":[{"b":"Acalanto","q":"5","l":"11","r":"R Acan","d":49.54,"c":"HIGH","lat":-16.7329485,"lng":-49.2264841,"si":262847}],"ACALANTO|8|14":[{"b":"Acalanto","q":"8","l":"14","r":"R Naoqui","d":19.76,"c":"HIGH","lat":-16.7347386,"lng":-49.227281,"si":289263}],"ACALANTO|8|18":[{"b":"Acalanto","q":"8","l":"18","r":"R Naoqui","d":18.41,"c":"HIGH","lat":-16.7348678,"lng":-49.2279013,"si":289264}],"ACALANTO|8|APM C19":[{"b":"Acalanto","q":"8","l":"APM-C19","r":"R Anarcan","d":8.55,"c":"HIGH","lat":-16.7359185,"lng":-49.2278167,"si":289354}],"ACALANTO|6|17":[{"b":"Acalanto","q":"6","l":"17","r":"AV Angélica","d":16.49,"c":"HIGH","lat":-16.7335082,"lng":-49.228624,"si":316233}],"ACALANTO|6|18":[{"b":"Acalanto","q":"6","l":"18","r":"R Diaran","d":28.2,"c":"HIGH","lat":-16.733413,"lng":-49.2284295,"si":316234}],"ACALANTO|6|19":[{"b":"Acalanto","q":"6","l":"19","r":"R Diaran","d":30.83,"c":"HIGH","lat":-16.7333585,"lng":-49.2282306,"si":316235}],"ACALANTO|6|20":[{"b":"Acalanto","q":"6","l":"20","r":"R Diaran","d":30.9,"c":"HIGH","lat":-16.7334417,"lng":-49.2280246,"si":316236}],"ACALANTO|6|12":[{"b":"Acalanto","q":"6","l":"12","r":"R Maiti","d":10.25,"c":"HIGH","lat":-16.7336268,"lng":-49.2277695,"si":316237}],"ACALANTO|6|14":[{"b":"Acalanto","q":"6","l":"14","r":"R Maiti","d":29.22,"c":"HIGH","lat":-16.733234,"lng":-49.2276964,"si":316238}],"ACALANTO|6|16":[{"b":"Acalanto","q":"6","l":"16","r":"R Maiti","d":16.55,"c":"HIGH","lat":-16.7332554,"lng":-49.2272915,"si":316239}],"ACALANTO|6|22":[{"b":"Acalanto","q":"6","l":"22","r":"R Diaran","d":15.4,"c":"HIGH","lat":-16.7338745,"lng":-49.2281272,"si":316240}],"ACALANTO|6|24":[{"b":"Acalanto","q":"6","l":"24","r":"R Diaran","d":20.89,"c":"HIGH","lat":-16.7338723,"lng":-49.2284618,"si":316242}],"ACALANTO|6|25":[{"b":"Acalanto","q":"6","l":"25","r":"AV Angélica","d":16.52,"c":"HIGH","lat":-16.7341899,"lng":-49.2284089,"si":316243}],"ACALANTO|6|26":[{"b":"Acalanto","q":"6","l":"26","r":"R Goti","d":25,"c":"HIGH","lat":-16.734069,"lng":-49.2282079,"si":316244}],"ACALANTO|6|27":[{"b":"Acalanto","q":"6","l":"27","r":"R Goti","d":11.63,"c":"HIGH","lat":-16.7340334,"lng":-49.228037,"si":316245}],"ACALANTO|6|9":[{"b":"Acalanto","q":"6","l":"9","r":"R Maiti","d":16.11,"c":"HIGH","lat":-16.7335454,"lng":-49.2272314,"si":316246}],"ACALANTO|6|10":[{"b":"Acalanto","q":"6","l":"10","r":"R Maiti","d":27.36,"c":"HIGH","lat":-16.7336818,"lng":-49.2273518,"si":316247}],"ACALANTO|6|11":[{"b":"Acalanto","q":"6","l":"11","r":"R Maiti","d":12.36,"c":"HIGH","lat":-16.7337437,"lng":-49.2275951,"si":316248}],"ACALANTO|6|6":[{"b":"Acalanto","q":"6","l":"6","r":"R Cirro","d":9.97,"c":"HIGH","lat":-16.7339284,"lng":-49.2275787,"si":316249}],"ACALANTO|6|7":[{"b":"Acalanto","q":"6","l":"7","r":"R Cirro","d":28.42,"c":"HIGH","lat":-16.73386,"lng":-49.2273144,"si":316250}],"ACALANTO|6|8":[{"b":"Acalanto","q":"6","l":"8","r":"R Cirro","d":17.08,"c":"HIGH","lat":-16.7339283,"lng":-49.2271427,"si":316251}],"ACALANTO|6|5":[{"b":"Acalanto","q":"6","l":"5","r":"R Cirro","d":11.38,"c":"HIGH","lat":-16.7341121,"lng":-49.2276479,"si":316252}],"ACALANTO|6|28":[{"b":"Acalanto","q":"6","l":"28","r":"R Goti","d":12.41,"c":"HIGH","lat":-16.7341601,"lng":-49.2278533,"si":316253}],"ACALANTO|6|32":[{"b":"Acalanto","q":"6","l":"32","r":"AV Angélica","d":17.89,"c":"HIGH","lat":-16.7345462,"lng":-49.2282784,"si":316254}],"ACALANTO|6|31":[{"b":"Acalanto","q":"6","l":"31","r":"R Naoqui","d":16.79,"c":"HIGH","lat":-16.7345847,"lng":-49.228093,"si":316255}],"ACALANTO|6|1":[{"b":"Acalanto","q":"6","l":"1","r":"R Cirro","d":18.32,"c":"HIGH","lat":-16.7342441,"lng":-49.2270863,"si":316256}],"ACALANTO|6|2":[{"b":"Acalanto","q":"6","l":"2","r":"R Naoqui","d":17.54,"c":"HIGH","lat":-16.7343728,"lng":-49.2271959,"si":316257}],"ACALANTO|6|3":[{"b":"Acalanto","q":"6","l":"3","r":"R Naoqui","d":18.48,"c":"HIGH","lat":-16.734417,"lng":-49.2274276,"si":316258}],"ACALANTO|6|4":[{"b":"Acalanto","q":"6","l":"4","r":"R Cirro","d":30.5,"c":"HIGH","lat":-16.7343303,"lng":-49.2276086,"si":316259}],"ACALANTO|6|29":[{"b":"Acalanto","q":"6","l":"29","r":"R Goti","d":31.36,"c":"HIGH","lat":-16.7343551,"lng":-49.2277675,"si":316260}],"ACALANTO|3|1":[{"b":"Acalanto","q":"3","l":"1","r":"R Ocanan","d":22.85,"c":"HIGH","lat":-16.7320334,"lng":-49.2271648,"si":323533}],"ACALANTO|3|10":[{"b":"Acalanto","q":"3","l":"10","r":"AL Inan","d":28.64,"c":"HIGH","lat":-16.7314729,"lng":-49.2272638,"si":323536}],"ACALANTO|3|13 14":[{"b":"Acalanto","q":"3","l":"13/14","r":"R Iatan","d":29.7,"c":"HIGH","lat":-16.7311007,"lng":-49.2270901,"si":323537}],"ACALANTO|3|2":[{"b":"Acalanto","q":"3","l":"2","r":"R Ocanan","d":23.06,"c":"HIGH","lat":-16.7319865,"lng":-49.2269783,"si":323542}],"ACALANTO|3|3":[{"b":"Acalanto","q":"3","l":"3","r":"R Ocanan","d":22.77,"c":"HIGH","lat":-16.7319641,"lng":-49.2268739,"si":323543}],"ACALANTO|3|4":[{"b":"Acalanto","q":"3","l":"4","r":"R Ocanan","d":22.49,"c":"HIGH","lat":-16.7319329,"lng":-49.2267338,"si":323544}],"ACALANTO|3|5":[{"b":"Acalanto","q":"3","l":"5","r":"R Ocanan","d":22.09,"c":"HIGH","lat":-16.7318982,"lng":-49.2265746,"si":323545}],"ACALANTO|8|30":[{"b":"Acalanto","q":"8","l":"30","r":"R Anarcan","d":26.62,"c":"HIGH","lat":-16.7360039,"lng":-49.2275109,"si":337037}],"ACALANTO|8|31":[{"b":"Acalanto","q":"8","l":"31","r":"AV Bela Vista","d":23.01,"c":"HIGH","lat":-16.7360551,"lng":-49.2276196,"si":337038}],"ACALANTO|8|2":[{"b":"Acalanto","q":"8","l":"2","r":"R Cuaqui","d":29.01,"c":"HIGH","lat":-16.7358683,"lng":-49.2267741,"si":337039}],"ACALANTO|8|3":[{"b":"Acalanto","q":"8","l":"3","r":"R Cuaqui","d":29.42,"c":"HIGH","lat":-16.7359071,"lng":-49.2269717,"si":337040}],"ACALANTO|8|5":[{"b":"Acalanto","q":"8","l":"5","r":"R Cuaqui","d":12.88,"c":"HIGH","lat":-16.7356017,"lng":-49.2272308,"si":337041}],"ACALANTO|8|4":[{"b":"Acalanto","q":"8","l":"4","r":"R Cuaqui","d":28.45,"c":"HIGH","lat":-16.735803,"lng":-49.2271802,"si":337043}],"ACALANTO|8|29":[{"b":"Acalanto","q":"8","l":"29","r":"R Anarcan","d":29.1,"c":"HIGH","lat":-16.7358447,"lng":-49.2273546,"si":337044}],"ACALANTO|5|3":[{"b":"Acalanto","q":"5","l":"3","r":"R Ocanan","d":17.32,"c":"HIGH","lat":-16.732281,"lng":-49.2266397,"si":337045}],"ACALANTO|5|2":[{"b":"Acalanto","q":"5","l":"2","r":"R Ocanan","d":17.35,"c":"HIGH","lat":-16.73235,"lng":-49.2269249,"si":337046}],"ACALANTO|5|1":[{"b":"Acalanto","q":"5","l":"1","r":"R Acan","d":18.84,"c":"HIGH","lat":-16.7324692,"lng":-49.227074,"si":341406}],"ACALANTO|5|4":[{"b":"Acalanto","q":"5","l":"4","r":"R Ocanan","d":33.44,"c":"HIGH","lat":-16.7323869,"lng":-49.2264564,"si":341407}],"ACALANTO|5|5":[{"b":"Acalanto","q":"5","l":"5","r":"R Acan","d":33.43,"c":"HIGH","lat":-16.7326162,"lng":-49.226413,"si":341408}],"ACALANTO|5|6":[{"b":"Acalanto","q":"5","l":"6","r":"R Acan","d":30.38,"c":"HIGH","lat":-16.7327743,"lng":-49.2265388,"si":341409}],"ACALANTO|5|7":[{"b":"Acalanto","q":"5","l":"7","r":"R Acan","d":25.86,"c":"HIGH","lat":-16.7328232,"lng":-49.2268061,"si":341410}],"ACALANTO|5|8":[{"b":"Acalanto","q":"5","l":"8","r":"R Acan","d":17.73,"c":"HIGH","lat":-16.7327832,"lng":-49.226962,"si":341411}],"ACALANTO|5|9":[{"b":"Acalanto","q":"5","l":"9","r":"R Uaxito","d":18.93,"c":"HIGH","lat":-16.7331336,"lng":-49.2268991,"si":341412}],"ACALANTO|5|10":[{"b":"Acalanto","q":"5","l":"10","r":"R Uaxito","d":26.46,"c":"HIGH","lat":-16.7330239,"lng":-49.2267415,"si":341413}],"ACALANTO|5|12":[{"b":"Acalanto","q":"5","l":"12","r":"R Uaxito","d":28.84,"c":"HIGH","lat":-16.7330523,"lng":-49.2263349,"si":341415}],"ACALANTO|5|13":[{"b":"Acalanto","q":"5","l":"13","r":"R Uaxito","d":32.82,"c":"HIGH","lat":-16.7332934,"lng":-49.2262427,"si":341416}],"ACALANTO|5|14":[{"b":"Acalanto","q":"5","l":"14","r":"R Uaxito","d":31.71,"c":"HIGH","lat":-16.7334728,"lng":-49.2263995,"si":341417}],"ACALANTO|5|15":[{"b":"Acalanto","q":"5","l":"15","r":"R Uaxito","d":27.62,"c":"HIGH","lat":-16.7335061,"lng":-49.2266507,"si":341418}],"ACALANTO|5|16":[{"b":"Acalanto","q":"5","l":"16","r":"R Uaxito","d":19.3,"c":"HIGH","lat":-16.7334645,"lng":-49.2267953,"si":341419}],"ACALANTO|5|17":[{"b":"Acalanto","q":"5","l":"17","r":"R Binon","d":18.87,"c":"HIGH","lat":-16.7338141,"lng":-49.2267249,"si":341420}],"ACALANTO|5|18":[{"b":"Acalanto","q":"5","l":"18","r":"R Binon","d":26.3,"c":"HIGH","lat":-16.7337122,"lng":-49.226589,"si":341421}],"ACALANTO|5|19":[{"b":"Acalanto","q":"5","l":"19","r":"R Binon","d":27.94,"c":"HIGH","lat":-16.7336492,"lng":-49.2263617,"si":341422}],"ACALANTO|5|20":[{"b":"Acalanto","q":"5","l":"20","r":"R Binon","d":27.51,"c":"HIGH","lat":-16.7337409,"lng":-49.2261619,"si":341423}],"ACALANTO|5|21":[{"b":"Acalanto","q":"5","l":"21","r":"R Binon","d":27.86,"c":"HIGH","lat":-16.7339798,"lng":-49.2261103,"si":341424}],"ACALANTO|5|22":[{"b":"Acalanto","q":"5","l":"22","r":"R Naoqui","d":19.19,"c":"HIGH","lat":-16.7341385,"lng":-49.2262269,"si":341425}],"ACALANTO|5|23":[{"b":"Acalanto","q":"5","l":"23","r":"R Naoqui","d":20.18,"c":"HIGH","lat":-16.7341959,"lng":-49.2265234,"si":341426}],"ACALANTO|5|24":[{"b":"Acalanto","q":"5","l":"24","r":"R Binon","d":18.8,"c":"HIGH","lat":-16.7341524,"lng":-49.2266727,"si":341427}],"ACALANTO|8|22":[{"b":"Acalanto","q":"8","l":"22","r":"R Ueriri","d":15.21,"c":"HIGH","lat":-16.7353489,"lng":-49.2276791,"si":341461}],"ACALANTO|8|26":[{"b":"Acalanto","q":"8","l":"26","r":"R Anarcan","d":18.31,"c":"HIGH","lat":-16.7355431,"lng":-49.2276958,"si":341462}],"ACALANTO|8|27":[{"b":"Acalanto","q":"8","l":"27","r":"R Anarcan","d":10.72,"c":"HIGH","lat":-16.7355247,"lng":-49.227603,"si":341463}],"ACALANTO|8|25":[{"b":"Acalanto","q":"8","l":"25","r":"AV Angélica","d":20.14,"c":"HIGH","lat":-16.7356458,"lng":-49.2279116,"si":341464}],"ACALANTO|8|24":[{"b":"Acalanto","q":"8","l":"24","r":"R Ueriri","d":20.69,"c":"HIGH","lat":-16.7353499,"lng":-49.2279839,"si":341465}],"ACALANTO|8|8":[{"b":"Acalanto","q":"8","l":"8","r":"R Cuaqui","d":15.91,"c":"HIGH","lat":-16.7354353,"lng":-49.2267271,"si":341466}],"ACALANTO|8|7":[{"b":"Acalanto","q":"8","l":"7","r":"R Cuaqui","d":26.88,"c":"HIGH","lat":-16.7353782,"lng":-49.2269011,"si":341467}],"ACALANTO|8|10":[{"b":"Acalanto","q":"8","l":"10","r":"R Deacon","d":27.58,"c":"HIGH","lat":-16.7351694,"lng":-49.226918,"si":341468}],"ACALANTO|8|9":[{"b":"Acalanto","q":"8","l":"9","r":"R Deacon","d":15.15,"c":"HIGH","lat":-16.7350358,"lng":-49.2268161,"si":341469}],"ACALANTO|8|11":[{"b":"Acalanto","q":"8","l":"11","r":"R Deacon","d":17.62,"c":"HIGH","lat":-16.7352046,"lng":-49.227085,"si":341470}],"ACALANTO|8|6":[{"b":"Acalanto","q":"8","l":"6","r":"R Cuaqui","d":11.64,"c":"HIGH","lat":-16.7354148,"lng":-49.2271073,"si":341471}],"ACALANTO|8|1":[{"b":"Acalanto","q":"8","l":"1","r":"R Cuaqui","d":15.97,"c":"HIGH","lat":-16.7357207,"lng":-49.2266769,"si":341568}]}}